gabriel_client/__init__.py
gabriel_client/gabriel_client.py
gabriel_client/measurement_client.py
gabriel_client/opencv_adapter.py
gabriel_client/push_source.py
gabriel_client/websocket_client.py
gabriel_client/zeromq_client.py
gabriel_client-4.1.4.dist-info/METADATA
gabriel_client-4.1.4.dist-info/WHEEL
gabriel_client-4.1.4.dist-info/licenses/LICENSE
gabriel_client-4.1.4.dist-info/RECORD
